data/user_agents.json
venpo/cli.py
venpo/main.py
venpo_demo.gif
venpo-0.2.4.dist-info/entry_points.txt
venpo-0.2.4.dist-info/LICENSE.md
venpo-0.2.4.dist-info/WHEEL
venpo-0.2.4.dist-info/METADATA
venpo-0.2.4.dist-info/RECORD
